{
  "success": [
    {
      "name": "학교법인 고려중앙학원 고려대학교의과대학부속병원(안암병원)",
      "url": "http://anam.kumc.or.kr/main/index.do",
      "pages": 1,
      "total_text": 117,
      "specialty": ""
    },
    {
      "name": "사회복지법인 성가소비녀회 성가복지병원",
      "url": "http://www.sgbokji.or.kr",
      "pages": 1,
      "total_text": 1406,
      "specialty": ""
    },
    {
      "name": "의료법인 우신향병원",
      "url": "http://www.wshmc.co.kr",
      "pages": 9,
      "total_text": 10440,
      "specialty": ""
    },
    {
      "name": "동서요양병원",
      "url": "http://www.dsh.co.kr",
      "pages": 2,
      "total_text": 2783,
      "specialty": ""
    },
    {
      "name": "보문효사랑요양병원",
      "url": "http://www.xn--9i2b72ed9a6d71r3wi1yb1nl19i.com/",
      "pages": 9,
      "total_text": 10062,
      "specialty": ""
    },
    {
      "name": "새마음요양병원",
      "url": "http://www.haesol.org",
      "pages": 2,
      "total_text": 2433,
      "specialty": ""
    },
    {
      "name": "의료법인참예원의료재단 성북참요양병원",
      "url": "http://www.seongbukchamhospital.co.kr",
      "pages": 1,
      "total_text": 441,
      "specialty": ""
    },
    {
      "name": "고운숨결내과의원",
      "url": "http://www.sumsori.com/",
      "pages": 1,
      "total_text": 1287,
      "specialty": ""
    },
    {
      "name": "다이브의원",
      "url": "https://dybeclinic.com",
      "pages": 3,
      "total_text": 4581,
      "specialty": ""
    },
    {
      "name": "돈암고운세상피부과의원",
      "url": "http://www.beautyforever.co.kr",
      "pages": 1,
      "total_text": 1150,
      "specialty": ""
    },
    {
      "name": "맑은맥외과의원",
      "url": "http://www.cleanvessel.co.kr",
      "pages": 1,
      "total_text": 243,
      "specialty": ""
    },
    {
      "name": "메이저성형외과의원",
      "url": "http://majorskin.co.kr",
      "pages": 1,
      "total_text": 2422,
      "specialty": ""
    },
    {
      "name": "메이저피부과의원",
      "url": "http://majorskin.co.kr",
      "pages": 1,
      "total_text": 2422,
      "specialty": ""
    },
    {
      "name": "서울탑정신건강의학과의원",
      "url": "http://www.seouljunior.co.kr",
      "pages": 1,
      "total_text": 1575,
      "specialty": ""
    },
    {
      "name": "열린산부인과의원",
      "url": "http://www.womenclinic.co.kr/",
      "pages": 1,
      "total_text": 350,
      "specialty": ""
    },
    {
      "name": "우리기쁜산부인과의원",
      "url": "http://www.wejoyful.com/",
      "pages": 1,
      "total_text": 1146,
      "specialty": ""
    },
    {
      "name": "지인산부인과의원",
      "url": "http://www.huu.kr",
      "pages": 4,
      "total_text": 7536,
      "specialty": ""
    },
    {
      "name": "차앤박피부과의원",
      "url": "http://www.cnpskin.com",
      "pages": 9,
      "total_text": 48928,
      "specialty": ""
    },
    {
      "name": "최현주영상의학과의원",
      "url": "http://www.drbreast.co.kr/",
      "pages": 1,
      "total_text": 423,
      "specialty": ""
    },
    {
      "name": "팔레트정신건강의학과의원",
      "url": "https://spiral-charger-7b9.notion.site/2a39b1a25e0280afafdddbdb5847e6b1",
      "pages": 9,
      "total_text": 2002,
      "specialty": ""
    },
    {
      "name": "휴앤힐정신건강의학과의원",
      "url": "https://hueandheal.modoo.at/",
      "pages": 9,
      "total_text": 2376,
      "specialty": ""
    },
    {
      "name": "빈센트치과의원",
      "url": "http://www.vincentdent.com",
      "pages": 1,
      "total_text": 607,
      "specialty": ""
    },
    {
      "name": "서울S플러스치과의원",
      "url": "http://www.seoulsplus.com/",
      "pages": 1,
      "total_text": 5637,
      "specialty": ""
    },
    {
      "name": "안암엘와이엔치과의원",
      "url": "http://www.lyn.kr/",
      "pages": 2,
      "total_text": 2632,
      "specialty": ""
    },
    {
      "name": "연세정치과의원",
      "url": "https://periojung.com",
      "pages": 4,
      "total_text": 4024,
      "specialty": ""
    },
    {
      "name": "연세휴치과의원",
      "url": "https://www.huedental.co.kr",
      "pages": 9,
      "total_text": 1931,
      "specialty": ""
    },
    {
      "name": "규장한의원",
      "url": "https://kyujang.modoo.at/",
      "pages": 9,
      "total_text": 2376,
      "specialty": ""
    }
  ],
  "js_needed": [
    {
      "name": "서울척병원",
      "url": "http://www.chukhospital.com",
      "main_text_len": 5,
      "specialty": ""
    },
    {
      "name": "의료법인유라의료재단 온누리요양병원",
      "url": "http://www.onnurihosp.co.kr/seongbuk/index.asp",
      "main_text_len": 0,
      "specialty": ""
    },
    {
      "name": "365엠씨의원",
      "url": "http://www.365mc.co.kr/",
      "main_text_len": 0,
      "specialty": ""
    },
    {
      "name": "갤러리아피부과의원",
      "url": "https://galleriaskinsb.com",
      "main_text_len": 0,
      "specialty": ""
    },
    {
      "name": "굿모닝이비인후과의원",
      "url": "http://www.coclean.co.kr",
      "main_text_len": 8,
      "specialty": ""
    },
    {
      "name": "김앤김안과의원",
      "url": "http://www.kimkimeye.com/index.php",
      "main_text_len": 0,
      "specialty": ""
    },
    {
      "name": "김윤호서울외과의원",
      "url": "http://www.bestsurgery.co.kr/",
      "main_text_len": 0,
      "specialty": ""
    },
    {
      "name": "듀오피부과의원",
      "url": "http://www.duoclinic.co.kr",
      "main_text_len": 0,
      "specialty": ""
    },
    {
      "name": "맑은의원",
      "url": "http://",
      "main_text_len": 0,
      "specialty": ""
    },
    {
      "name": "미래의원",
      "url": "http://www.miraeskin.co.kr",
      "main_text_len": 0,
      "specialty": ""
    },
    {
      "name": "성북성심신경과의원",
      "url": "http://www.sbsshp.co.kr",
      "main_text_len": 0,
      "specialty": ""
    },
    {
      "name": "성북탑내과의원",
      "url": "https://www.seongbuktop.co.kr",
      "main_text_len": 0,
      "specialty": ""
    },
    {
      "name": "성북탑정형외과신경외과의원",
      "url": "https://성북탑.co.kr",
      "main_text_len": 0,
      "specialty": ""
    },
    {
      "name": "송이여성의원",
      "url": "http://songeclinic.co.kr",
      "main_text_len": 0,
      "specialty": ""
    },
    {
      "name": "에스메디센터내과외과의원",
      "url": "http://www.s-medicenter.com/intro.asp",
      "main_text_len": 0,
      "specialty": ""
    },
    {
      "name": "연세속편한의원",
      "url": "http://www.ezsok.com",
      "main_text_len": 0,
      "specialty": ""
    },
    {
      "name": "오라쁘띠의원",
      "url": "http://www.hhclinic.co.kr",
      "main_text_len": 0,
      "specialty": ""
    },
    {
      "name": "우노비뇨기과의원",
      "url": "http://www.unoman.co.kr/",
      "main_text_len": 0,
      "specialty": ""
    },
    {
      "name": "이소진의원",
      "url": "http://www.leesojin.co.kr/index.asp",
      "main_text_len": 0,
      "specialty": ""
    },
    {
      "name": "뉴연세치과의원",
      "url": "http://www.new-yonsei.com",
      "main_text_len": 0,
      "specialty": ""
    },
    {
      "name": "닥터민치과의원",
      "url": "http://www.doctormin.co.kr",
      "main_text_len": 0,
      "specialty": ""
    },
    {
      "name": "미보치과의원",
      "url": "http://blog.naver.com/goongsoo",
      "main_text_len": 28,
      "specialty": ""
    },
    {
      "name": "서울명인치과의원",
      "url": "http://www.dentalmaster.co.kr/",
      "main_text_len": 88,
      "specialty": ""
    },
    {
      "name": "서울하이안치과의원",
      "url": "http://www.highan.com/gireum",
      "main_text_len": 46,
      "specialty": ""
    },
    {
      "name": "이스터치과의원",
      "url": "http://www.easterdent.com/",
      "main_text_len": 0,
      "specialty": ""
    },
    {
      "name": "경희강한의원",
      "url": "http://www.khkang.co.kr",
      "main_text_len": 0,
      "specialty": ""
    },
    {
      "name": "민들레한의원",
      "url": "http://",
      "main_text_len": 0,
      "specialty": ""
    },
    {
      "name": "백산한의원",
      "url": "http://www.paiksan.co.kr/",
      "main_text_len": 0,
      "specialty": ""
    },
    {
      "name": "해오름한의원",
      "url": "http://",
      "main_text_len": 0,
      "specialty": ""
    },
    {
      "name": "형제한의원",
      "url": "http://",
      "main_text_len": 0,
      "specialty": ""
    },
    {
      "name": "활짝한의원",
      "url": "http://gungilhani.site",
      "main_text_len": 0,
      "specialty": ""
    }
  ],
  "failed": []
}